opencap_visualizer/__init__.py
opencap_visualizer/api.py
opencap_visualizer/cli.py
opencap_visualizer-1.1.2.dist-info/licenses/LICENSE
opencap_visualizer-1.1.2.dist-info/METADATA
opencap_visualizer-1.1.2.dist-info/WHEEL
opencap_visualizer-1.1.2.dist-info/entry_points.txt
opencap_visualizer-1.1.2.dist-info/top_level.txt
opencap_visualizer-1.1.2.dist-info/RECORD
