Metadata-Version: 2.4
Name: opencap-visualizer
Version: 1.1.2
Summary: Tool for creating videos from OpenCap biomechanics data with both CLI and Python API
Home-page: https://github.com/utahmobl/opencap-visualizer
Author: Selim Gilon
Author-email: Selim Gilon <selim.gilon@utah.edu>
License: MIT
Project-URL: Homepage, https://github.com/utahmobl/opencap-visualizer
Project-URL: Bug Reports, https://github.com/utahmobl/opencap-visualizer/issues
Project-URL: Source, https://github.com/utahmobl/opencap-visualizer
Project-URL: Web App, https://opencap-visualizer.onrender.com/
Keywords: biomechanics,motion-capture,visualization,video,opencap,opensim
Platform: any
Classifier: Development Status :: 4 - Beta
Classifier: Intended Audience :: Science/Research
Classifier: Topic :: Scientific/Engineering :: Visualization
Classifier: Topic :: Scientific/Engineering :: Medical Science Apps.
Classifier: License :: OSI Approved :: MIT License
Classifier: Programming Language :: Python :: 3
Classifier: Programming Language :: Python :: 3.7
Classifier: Programming Language :: Python :: 3.8
Classifier: Programming Language :: Python :: 3.9
Classifier: Programming Language :: Python :: 3.10
Classifier: Programming Language :: Python :: 3.11
Classifier: Programming Language :: Python :: 3.12
Classifier: Operating System :: OS Independent
Classifier: Environment :: Console
Requires-Python: >=3.7
License-File: LICENSE
Requires-Dist: playwright>=1.40.0
Requires-Dist: aiohttp>=3.8.0
Requires-Dist: pathlib2>=2.3.0; python_version < "3.4"
Provides-Extra: dev
Requires-Dist: pytest>=6.0; extra == "dev"
Requires-Dist: black>=22.0; extra == "dev"
Requires-Dist: flake8>=4.0; extra == "dev"
Requires-Dist: mypy>=0.900; extra == "dev"
Provides-Extra: ffmpeg
Requires-Dist: ffmpeg-python>=0.2.0; extra == "ffmpeg"
Dynamic: author
Dynamic: home-page
Dynamic: license-file
Dynamic: platform
Dynamic: requires-python
